gradient_agents/__init__.py
gradient_agents/decorator.py
gradient_agents/streaming.py
gradient_agents/_vendor/__init__.py
gradient_agents/cli/__init__.py
gradient_agents/cli/cli.py
gradient_agents/cli/agent/__init__.py
gradient_agents/cli/agent/deploy_service.py
gradient_agents/cli/agent/direct_launch_service.py
gradient_agents/cli/agent/env_utils.py
gradient_agents/cli/agent/launch_service.py
gradient_agents/cli/agent/mock_deploy_service.py
gradient_agents/cli/agent/api/__init__.py
gradient_agents/cli/agent/api/aiohttp_client.py
gradient_agents/cli/agent/api/auth.py
gradient_agents/cli/agent/api/digitalocean_traces.py
gradient_agents/cli/agent/api/examples.py
gradient_agents/cli/agent/api/factory.py
gradient_agents/cli/agent/api/http_client.py
gradient_agents/cli/agent/api/traces_service.py
gradient_agents/cli/config/config_reader.py
gradient_agents/cli/config/config_service.py
gradient_agents/cli/config/yaml_config_reader.py
gradient_agents/cli/config/yaml_config_service.py
gradient_agents/runtime/__init__.py
gradient_agents/runtime/context.py
gradient_agents/runtime/interfaces.py
gradient_agents/runtime/langgraph_instrumentor.py
gradient_agents/runtime/manager.py
gradient_agents/runtime/tracker.py
gradient_agents-0.2.2.dist-info/METADATA
gradient_agents-0.2.2.dist-info/WHEEL
gradient_agents-0.2.2.dist-info/entry_points.txt
gradient_agents-0.2.2.dist-info/top_level.txt
gradient_agents-0.2.2.dist-info/RECORD
